asmy/__init__.py
asmy/assembler.py
asmy/chip8.py
asmy/gmc4.py
asmy/lmc.py
asmy/mos6502.py
asmy/sweet16.py
asmy-0.1.2.dist-info/licenses/LICENSE
asmy-0.1.2.dist-info/METADATA
asmy-0.1.2.dist-info/WHEEL
asmy-0.1.2.dist-info/top_level.txt
asmy-0.1.2.dist-info/RECORD
