Metadata-Version: 2.4
Name: asmy
Version: 0.1.2
Summary: Python-based multi-architecture assembler
Author-email: Serge Zaitsev <hello@zserge.com>
License: MIT
Classifier: License :: OSI Approved :: MIT License
Classifier: Programming Language :: Python :: 3
Classifier: Topic :: Software Development :: Assemblers
License-File: LICENSE
Dynamic: license-file
